shellix/__init__.py
shellix/__main__.py
shellix/ai_core.py
shellix/credentials_loader.py
shellix/memory.py
shellix/shell_tool.py
shellix/write_tool.py
shellix-0.3.2.dist-info/LICENSE
shellix-0.3.2.dist-info/METADATA
shellix-0.3.2.dist-info/WHEEL
shellix-0.3.2.dist-info/entry_points.txt
shellix-0.3.2.dist-info/RECORD
