Metadata-Version: 2.3
Name: shellix
Version: 0.3.2
Summary: Terminal AI assistant for development
License: MIT
Author: Aydar Akhmetzyanov
Author-email: aydar.tech@gmail.com
Requires-Python: >=3.9,<4.0
Classifier: License :: OSI Approved :: MIT License
Classifier: Programming Language :: Python :: 3
Classifier: Programming Language :: Python :: 3.9
Classifier: Programming Language :: Python :: 3.10
Classifier: Programming Language :: Python :: 3.11
Classifier: Programming Language :: Python :: 3.12
Classifier: Programming Language :: Python :: 3.13
Requires-Dist: langchain-community (>=0.3.19,<0.4.0)
Requires-Dist: langchain-experimental (>=0.3.4,<0.4.0)
Requires-Dist: langchain-openai (>=0.3.7,<0.4.0)
Requires-Dist: langgraph (>=0.3.5,<0.4.0)
Requires-Dist: tavily-python (>=0.5.1,<0.6.0)
